{
  "swagger": "2.0",
  "info": {
    "title": "Youtube 2.0 Express API with Swagger",
    "description": "Automatically generated Swagger documentation",
    "version": "1.0.0"
  },
  "host": "http://localhost:5000",
  "basePath": "/",
  "schemes": [
    "http"
  ],
  "paths": {
    "/api/v1/": {
      "get": {
        "description": "",
        "responses": {
          "default": {
            "description": ""
          }
        }
      }
    },
    "/api/v1/user/register": {
      "post": {
        "description": "",
        "responses": {
          "default": {
            "description": ""
          }
        }
      }
    },
    "/api/v1/user/login": {
      "post": {
        "description": "",
        "responses": {
          "default": {
            "description": ""
          }
        }
      }
    },
    "/api/v1/user/refresh-session": {
      "post": {
        "description": "",
        "responses": {
          "default": {
            "description": ""
          }
        }
      }
    },
    "/api/v1/user/profile": {
      "get": {
        "description": "",
        "parameters": [
          {
            "name": "Authorization",
            "in": "header",
            "type": "string"
          }
        ],
        "responses": {
          "default": {
            "description": ""
          }
        }
      },
      "patch": {
        "description": "",
        "parameters": [
          {
            "name": "Authorization",
            "in": "header",
            "type": "string"
          }
        ],
        "responses": {
          "default": {
            "description": ""
          }
        }
      }
    },
    "/api/v1/user/avatar": {
      "patch": {
        "description": "",
        "parameters": [
          {
            "name": "Authorization",
            "in": "header",
            "type": "string"
          }
        ],
        "responses": {
          "default": {
            "description": ""
          }
        }
      }
    },
    "/api/v1/user/cover-image": {
      "patch": {
        "description": "",
        "parameters": [
          {
            "name": "Authorization",
            "in": "header",
            "type": "string"
          }
        ],
        "responses": {
          "default": {
            "description": ""
          }
        }
      },
      "delete": {
        "description": "",
        "parameters": [
          {
            "name": "Authorization",
            "in": "header",
            "type": "string"
          }
        ],
        "responses": {
          "default": {
            "description": ""
          }
        }
      }
    },
    "/api/v1/user/channel/{username}": {
      "get": {
        "description": "",
        "parameters": [
          {
            "name": "username",
            "in": "path",
            "required": true,
            "type": "string"
          },
          {
            "name": "Authorization",
            "in": "header",
            "type": "string"
          }
        ],
        "responses": {
          "default": {
            "description": ""
          }
        }
      }
    },
    "/api/v1/user/watch-history": {
      "get": {
        "description": "",
        "parameters": [
          {
            "name": "Authorization",
            "in": "header",
            "type": "string"
          }
        ],
        "responses": {
          "default": {
            "description": ""
          }
        }
      }
    },
    "/api/v1/user/password/update": {
      "patch": {
        "description": "",
        "parameters": [
          {
            "name": "Authorization",
            "in": "header",
            "type": "string"
          }
        ],
        "responses": {
          "default": {
            "description": ""
          }
        }
      }
    },
    "/api/v1/user/logout": {
      "get": {
        "description": "",
        "parameters": [
          {
            "name": "Authorization",
            "in": "header",
            "type": "string"
          }
        ],
        "responses": {
          "default": {
            "description": ""
          }
        }
      }
    },
    "/api/v1/dashboard/stats": {
      "get": {
        "description": "",
        "parameters": [
          {
            "name": "Authorization",
            "in": "header",
            "type": "string"
          }
        ],
        "responses": {
          "default": {
            "description": ""
          }
        }
      }
    },
    "/api/v1/dashboard/videos": {
      "get": {
        "description": "",
        "parameters": [
          {
            "name": "Authorization",
            "in": "header",
            "type": "string"
          },
          {
            "name": "limit",
            "in": "query",
            "type": "string"
          },
          {
            "name": "page",
            "in": "query",
            "type": "string"
          }
        ],
        "responses": {
          "default": {
            "description": ""
          }
        }
      }
    },
    "/api/v1/video/": {
      "get": {
        "description": "",
        "parameters": [
          {
            "name": "page",
            "in": "query",
            "type": "string"
          },
          {
            "name": "limit",
            "in": "query",
            "type": "string"
          },
          {
            "name": "query",
            "in": "query",
            "type": "string"
          },
          {
            "name": "sortBy",
            "in": "query",
            "type": "string"
          },
          {
            "name": "sortType",
            "in": "query",
            "type": "string"
          },
          {
            "name": "userId",
            "in": "query",
            "type": "string"
          }
        ],
        "responses": {
          "default": {
            "description": ""
          }
        }
      }
    },
    "/api/v1/video/upload": {
      "post": {
        "description": "",
        "parameters": [
          {
            "name": "Authorization",
            "in": "header",
            "type": "string"
          },
          {
            "name": "body",
            "in": "body",
            "schema": {
              "type": "object",
              "properties": {
                "title": {
                  "example": "any"
                },
                "description": {
                  "example": "any"
                }
              }
            }
          }
        ],
        "responses": {
          "default": {
            "description": ""
          }
        }
      }
    },
    "/api/v1/comment/{videoId}": {
      "get": {
        "description": "",
        "parameters": [
          {
            "name": "videoId",
            "in": "path",
            "required": true,
            "type": "string"
          },
          {
            "name": "Authorization",
            "in": "header",
            "type": "string"
          },
          {
            "name": "page",
            "in": "query",
            "type": "string"
          },
          {
            "name": "limit",
            "in": "query",
            "type": "string"
          }
        ],
        "responses": {
          "default": {
            "description": ""
          }
        }
      },
      "post": {
        "description": "",
        "parameters": [
          {
            "name": "videoId",
            "in": "path",
            "required": true,
            "type": "string"
          },
          {
            "name": "Authorization",
            "in": "header",
            "type": "string"
          },
          {
            "name": "body",
            "in": "body",
            "schema": {
              "type": "object",
              "properties": {
                "content": {
                  "example": "any"
                }
              }
            }
          }
        ],
        "responses": {
          "default": {
            "description": ""
          }
        }
      }
    },
    "/api/v1/comment/{commentId}": {
      "delete": {
        "description": "",
        "parameters": [
          {
            "name": "commentId",
            "in": "path",
            "required": true,
            "type": "string"
          },
          {
            "name": "Authorization",
            "in": "header",
            "type": "string"
          }
        ],
        "responses": {
          "default": {
            "description": ""
          }
        }
      },
      "patch": {
        "description": "",
        "parameters": [
          {
            "name": "commentId",
            "in": "path",
            "required": true,
            "type": "string"
          },
          {
            "name": "Authorization",
            "in": "header",
            "type": "string"
          },
          {
            "name": "body",
            "in": "body",
            "schema": {
              "type": "object",
              "properties": {
                "content": {
                  "example": "any"
                }
              }
            }
          }
        ],
        "responses": {
          "default": {
            "description": ""
          }
        }
      }
    }
  }
}